lspm/__init__.py
lspm/__main__.py
lspm/cli.py
lspm/exceptions.py
lspm/interrupt_event_handler.py
lspm/laptop_smart_power_manager.py
lspm/parameters.py
lspm/smartplug/__init__.py
lspm/smartplug/base.py
lspm/smartplug/credentials.py
lspm/smartplug/tapo_plug.py
lspm-0.1.0.dist-info/LICENSE
lspm-0.1.0.dist-info/METADATA
lspm-0.1.0.dist-info/WHEEL
lspm-0.1.0.dist-info/entry_points.txt
lspm-0.1.0.dist-info/top_level.txt
lspm-0.1.0.dist-info/RECORD
