Metadata-Version: 2.1
Name: lspm
Version: 0.1.0
Summary: LSPM - Laptop Smart Power Manager
Home-page: https://github.com/ImaSet/laptop-smart-power-manager
Author: Imanol Setoain
Classifier: License :: OSI Approved :: MIT License
Classifier: Programming Language :: Python :: 3
Classifier: Programming Language :: Python :: 3.7
Classifier: Programming Language :: Python :: 3.8
Classifier: Programming Language :: Python :: 3.9
Classifier: Programming Language :: Python :: 3.10
Classifier: Typing :: Typed
Classifier: Operating System :: Microsoft :: Windows
Classifier: Operating System :: Unix
Classifier: Operating System :: MacOS
Requires-Python: >=3.7
License-File: LICENSE
Requires-Dist: keyring (==23.13.1)
Requires-Dist: psutil (==5.9.4)
Requires-Dist: PyP100 (==0.0.25)
Requires-Dist: pywin32 (==304)
